adpac_auth2/__init__.py
adpac_auth2/module.py
adpac_auth2-0.0.2.dist-info/METADATA
adpac_auth2-0.0.2.dist-info/WHEEL
adpac_auth2-0.0.2.dist-info/top_level.txt
adpac_auth2-0.0.2.dist-info/RECORD
